{"cookie":{"originalMaxAge":null,"expires":null,"secure":false,"httpOnly":false,"path":"/"},"cart":{"products":[{"slug":"tan-split-suede-casual-shoes-345711","picture":"4212022709_2_7_16.jpg","price":328,"name":"Tan Split Suede Casual Shoes","quantity":2},{"slug":"blue-split-suede-leather-loafers-345712","picture":"4402022400_2_7_16.jpg","price":255,"name":"Blue Split Suede Leather Loafers","quantity":1},{"slug":"limited-edition-embossed-leather-magic-card-holder-346499","picture":"1629039700_1_1_16.jpg","price":392,"name":"Limited Edition Embossed Leather Magic Card Holder","quantity":1}],"total":1303,"count":4},"__lastAccess":1554029520922}